{
    "paging": {
        "is_end": false,
        "previous": "https://www.zhihu.com/api/v4/members/bhuztez/answers?include=data%5B%2A%5D.content&limit=20&offset=200",
        "next": "https://www.zhihu.com/api/v4/members/bhuztez/answers?include=data%5B%2A%5D.content&limit=20&offset=240",
        "is_start": false,
        "totals": 442
    },
    "data": [
        {
            "type": "answer",
            "is_collapsed": false,
            "url": "https://www.zhihu.com/api/v4/answers/109848958",
            "thumbnail": "",
            "created_time": 1467877628,
            "updated_time": 1467877650,
            "id": 109848958,
            "excerpt": "嘘，说不定轮子哥到现在都不会用符号链接，不然他哪来那么多时间刷知乎",
            "content": "嘘，说不定轮子哥到现在都不会用符号链接，不然他哪来那么多时间刷知乎",
            "is_copyable": true,
            "author": {
                "is_org": false,
                "avatar_url_template": "https://pic3.zhimg.com/e59aeb8898c50a830976297787cdce86_{size}.jpg",
                "gender": 1,
                "type": "people",
                "url": "https://www.zhihu.com/api/v4/people/dcddea61834f6b2dcb515f393fe29575",
                "url_token": "bhuztez",
                "user_type": "people",
                "headline": "正在找工作 ...",
                "badge": [],
                "is_advertiser": false,
                "name": "bhuztez",
                "avatar_url": "https://pic3.zhimg.com/e59aeb8898c50a830976297787cdce86_is.jpg",
                "id": "dcddea61834f6b2dcb515f393fe29575"
            },
            "extras": "",
            "question": {
                "title": "如何评价微软高级工程师痴迷于soft link这一linux常见概念？",
                "updated_time": 1471315316,
                "url": "https://www.zhihu.com/api/v4/questions/48244674",
                "type": "question",
                "created": 1467876704,
                "question_type": "normal",
                "id": 48244674
            }
        },
        {
            "type": "answer",
            "is_collapsed": false,
            "url": "https://www.zhihu.com/api/v4/answers/109351116",
            "thumbnail": "",
            "created_time": 1467636390,
            "updated_time": 1467636390,
            "id": 109351116,
            "excerpt": "兼容老CPU高于一切 —— Andy Grove",
            "content": "兼容老CPU高于一切<br><br>—— Andy Grove",
            "is_copyable": true,
            "author": {
                "is_org": false,
                "avatar_url_template": "https://pic3.zhimg.com/e59aeb8898c50a830976297787cdce86_{size}.jpg",
                "gender": 1,
                "type": "people",
                "url": "https://www.zhihu.com/api/v4/people/dcddea61834f6b2dcb515f393fe29575",
                "url_token": "bhuztez",
                "user_type": "people",
                "headline": "正在找工作 ...",
                "badge": [],
                "is_advertiser": false,
                "name": "bhuztez",
                "avatar_url": "https://pic3.zhimg.com/e59aeb8898c50a830976297787cdce86_is.jpg",
                "id": "dcddea61834f6b2dcb515f393fe29575"
            },
            "extras": "",
            "question": {
                "title": "为什么Intel的CPU要规定加电时进入实模式？直接进保护模式不可以吗？",
                "updated_time": 1467681928,
                "url": "https://www.zhihu.com/api/v4/questions/48145032",
                "type": "question",
                "created": 1467628123,
                "question_type": "normal",
                "id": 48145032
            }
        },
        {
            "type": "answer",
            "is_collapsed": false,
            "url": "https://www.zhihu.com/api/v4/answers/108981153",
            "thumbnail": "",
            "created_time": 1467448382,
            "updated_time": 1467448382,
            "id": 108981153,
            "excerpt": "大部分介绍backpropagation的都忽略了最最关键一点。 比如有 Z = F o G，无论 o 是+ - * / 还是 ** \\frac{\\partial Z}{\\partial X}都能写成 A \\cdot \\frac{\\partial F}{\\partial X} + B \\cdot \\frac{\\partial G}{\\partial X} 的形式 否则像现在这样的 backpropagation 是不成立的",
            "content": "大部分介绍backpropagation的都忽略了最最关键一点。<br><br>比如有 Z = F o G，无论 o 是+ - * / 还是  **<br><br><img src=\"https://www.zhihu.com/equation?tex=%5Cfrac%7B%5Cpartial+Z%7D%7B%5Cpartial+X%7D\" alt=\"\\frac{\\partial Z}{\\partial X}\" eeimg=\"1\">都能写成  <img src=\"https://www.zhihu.com/equation?tex=A+%5Ccdot+%5Cfrac%7B%5Cpartial+F%7D%7B%5Cpartial+X%7D+%2B+B+%5Ccdot+%5Cfrac%7B%5Cpartial+G%7D%7B%5Cpartial+X%7D\" alt=\"A \\cdot \\frac{\\partial F}{\\partial X} + B \\cdot \\frac{\\partial G}{\\partial X}\" eeimg=\"1\"> 的形式<br><br>否则像现在这样的 backpropagation 是不成立的",
            "is_copyable": true,
            "author": {
                "is_org": false,
                "avatar_url_template": "https://pic3.zhimg.com/e59aeb8898c50a830976297787cdce86_{size}.jpg",
                "gender": 1,
                "type": "people",
                "url": "https://www.zhihu.com/api/v4/people/dcddea61834f6b2dcb515f393fe29575",
                "url_token": "bhuztez",
                "user_type": "people",
                "headline": "正在找工作 ...",
                "badge": [],
                "is_advertiser": false,
                "name": "bhuztez",
                "avatar_url": "https://pic3.zhimg.com/e59aeb8898c50a830976297787cdce86_is.jpg",
                "id": "dcddea61834f6b2dcb515f393fe29575"
            },
            "extras": "",
            "question": {
                "title": "如何直观的解释back propagation算法？",
                "updated_time": 1419492091,
                "url": "https://www.zhihu.com/api/v4/questions/27239198",
                "type": "question",
                "created": 1419443745,
                "question_type": "normal",
                "id": 27239198
            }
        },
        {
            "type": "answer",
            "is_collapsed": false,
            "url": "https://www.zhihu.com/api/v4/answers/108870276",
            "thumbnail": "",
            "created_time": 1467382145,
            "updated_time": 1467386502,
            "id": 108870276,
            "excerpt": "看github啊。 qinchao (Chao Qin (覃超)) · GitHub 。唯一他自己的仓库，GitHub - qinchao/gm-demo ，竟然把jar还有PID文件都commit进去了 bboczeng · GitHub 唯一有点内容的仓库 GitHub - bboczeng/Codes: Codes repository for projects finished/ongoing ，作为果粉，竟然把 .DS_Store 文件 commit 进去了 同时，他们都没放过.idea目录 难分胜负啊",
            "content": "看github啊。<br><br><a class=\" wrap external\" href=\"https://link.zhihu.com/?target=https%3A//github.com/qinchao\" target=\"_blank\" rel=\"nofollow noreferrer\">qinchao (Chao Qin (覃超)) · GitHub<i class=\"icon-external\"></i></a>。唯一他自己的仓库，<a class=\" wrap external\" href=\"https://link.zhihu.com/?target=https%3A//github.com/qinchao/gm-demo\" target=\"_blank\" rel=\"nofollow noreferrer\">GitHub - qinchao/gm-demo<i class=\"icon-external\"></i></a>，竟然把jar还有PID文件都commit进去了<br><br><a href=\"https://link.zhihu.com/?target=https%3A//github.com/bboczeng\" class=\" wrap external\" target=\"_blank\" rel=\"nofollow noreferrer\">bboczeng · GitHub<i class=\"icon-external\"></i></a> 唯一有点内容的仓库 <a class=\" wrap external\" href=\"https://link.zhihu.com/?target=https%3A//github.com/bboczeng/Codes\" target=\"_blank\" rel=\"nofollow noreferrer\">GitHub - bboczeng/Codes: Codes repository for projects finished/ongoing<i class=\"icon-external\"></i></a>，作为果粉，竟然把 .DS_Store 文件 commit 进去了<br><br>同时，他们都没放过.idea目录<br><br>难分胜负啊",
            "is_copyable": true,
            "author": {
                "is_org": false,
                "avatar_url_template": "https://pic3.zhimg.com/e59aeb8898c50a830976297787cdce86_{size}.jpg",
                "gender": 1,
                "type": "people",
                "url": "https://www.zhihu.com/api/v4/people/dcddea61834f6b2dcb515f393fe29575",
                "url_token": "bhuztez",
                "user_type": "people",
                "headline": "正在找工作 ...",
                "badge": [],
                "is_advertiser": false,
                "name": "bhuztez",
                "avatar_url": "https://pic3.zhimg.com/e59aeb8898c50a830976297787cdce86_is.jpg",
                "id": "dcddea61834f6b2dcb515f393fe29575"
            },
            "extras": "",
            "question": {
                "title": "覃超和曾博哪个人水平更高?",
                "updated_time": 1467533383,
                "url": "https://www.zhihu.com/api/v4/questions/48055416",
                "type": "question",
                "created": 1467378479,
                "question_type": "normal",
                "id": 48055416
            }
        },
        {
            "type": "answer",
            "is_collapsed": false,
            "url": "https://www.zhihu.com/api/v4/answers/107829335",
            "thumbnail": "",
            "created_time": 1466866923,
            "updated_time": 1466916497,
            "id": 107829335,
            "excerpt": "首先不要有layer的概念。 一个layer承担的功能太多了。所以不方便复用。你要搞不同的功能，就免不了要写个layer，麻烦啊。同时也使得这些框架的代码过于复杂。Convolution和Pooling就是同一个东西，还是有不少框架在这两个功能上重复了很多代码的。只考虑一维的情况，两者在J语言里，就是 +/ 和 >./ 的区别。 layer往往会隐藏一些东西，使得本来很容易看懂的，变得很难看懂了，让大忽悠有了存在的可能，说是什么模仿人脑云云。RG… ",
            "content": "首先不要有layer的概念。<br><br>一个layer承担的功能太多了。所以不方便复用。你要搞不同的功能，就免不了要写个layer，麻烦啊。同时也使得这些框架的代码过于复杂。Convolution和Pooling就是同一个东西，还是有不少框架在这两个功能上重复了很多代码的。只考虑一维的情况，两者在J语言里，就是 +/ 和 &gt;./ 的区别。<br><br>layer往往会隐藏一些东西，使得本来很容易看懂的，变得很难看懂了，让大忽悠有了存在的可能，说是什么模仿人脑云云。<a class=\"internal\" href=\"https://www.zhihu.com/question/46607672/answer/105261421\">RGB图像在CNN中如何进行convolution? - lixin liu 的回答</a><br><br>有了layer往往会意志不坚定，选择back-propagation，而不是实现自动求导，这会使得写一个新的的layer更麻烦。<br><br>二要引入统一的rank概念。否则操作多维数组会非常麻烦，不得不使用循环。<a class=\"internal\" href=\"https://www.zhihu.com/question/46616756/answer/106632200\">numpy中是否有什么办法扩展dot函数？ - 知乎用户的回答</a><br><br>三是不要引入mutable。毕竟一般数学公式里的变量都是immutable的，和编译器中用到的SSA形式是一样的。你引入了mutable，回头编译的时候还要再分析成immutable的，多此一举啊。<br><br>比如mxnet搞的那个symbolic api，尽管还是没有完全丢掉layer的概念，也是在往这个方向努力。只可惜他们编译原理都没考及格。提出了什么computation graph的概念。SSA形式下，变量之间自然就构成了DAG了。哪里需要自创新概念啊。古时候有个SISAL同样也是叫graph，除了没有自动求导，不知道比mxnet高到哪里去了。这也导致了mxnet的并行啊，节省内存啊，只能做粗粒度的，不能做细粒度的。<br><br>四是不要搞什么explicit parallelism。公式归公式计算归计算。不能因为你换了GPU，就要去改公式啊。torch那个nn就是个反例。<br><br>这样一来，好像就没的选了 ...",
            "is_copyable": true,
            "author": {
                "is_org": false,
                "avatar_url_template": "https://pic3.zhimg.com/e59aeb8898c50a830976297787cdce86_{size}.jpg",
                "gender": 1,
                "type": "people",
                "url": "https://www.zhihu.com/api/v4/people/dcddea61834f6b2dcb515f393fe29575",
                "url_token": "bhuztez",
                "user_type": "people",
                "headline": "正在找工作 ...",
                "badge": [],
                "is_advertiser": false,
                "name": "bhuztez",
                "avatar_url": "https://pic3.zhimg.com/e59aeb8898c50a830976297787cdce86_is.jpg",
                "id": "dcddea61834f6b2dcb515f393fe29575"
            },
            "extras": "",
            "question": {
                "title": "在众多的神经网络框架如chainer, caffe, torch，mxnet等之间如何做选择？",
                "updated_time": 1458626208,
                "url": "https://www.zhihu.com/api/v4/questions/35734807",
                "type": "question",
                "created": 1442577288,
                "question_type": "normal",
                "id": 35734807
            }
        },
        {
            "type": "answer",
            "is_collapsed": false,
            "url": "https://www.zhihu.com/api/v4/answers/107748964",
            "thumbnail": "",
            "created_time": 1466831877,
            "updated_time": 1466831877,
            "id": 107748964,
            "excerpt": "终于好了。不过，Fedora 24都已经发布了",
            "content": "终于好了。不过，Fedora 24都已经发布了",
            "is_copyable": true,
            "author": {
                "is_org": false,
                "avatar_url_template": "https://pic3.zhimg.com/e59aeb8898c50a830976297787cdce86_{size}.jpg",
                "gender": 1,
                "type": "people",
                "url": "https://www.zhihu.com/api/v4/people/dcddea61834f6b2dcb515f393fe29575",
                "url_token": "bhuztez",
                "user_type": "people",
                "headline": "正在找工作 ...",
                "badge": [],
                "is_advertiser": false,
                "name": "bhuztez",
                "avatar_url": "https://pic3.zhimg.com/e59aeb8898c50a830976297787cdce86_is.jpg",
                "id": "dcddea61834f6b2dcb515f393fe29575"
            },
            "extras": "",
            "question": {
                "title": "针对Fedora 23的RPM Fusion怎么还没好啊？",
                "updated_time": 1457847061,
                "url": "https://www.zhihu.com/api/v4/questions/41318976",
                "type": "question",
                "created": 1457840169,
                "question_type": "normal",
                "id": 41318976
            }
        },
        {
            "type": "answer",
            "is_collapsed": false,
            "url": "https://www.zhihu.com/api/v4/answers/107718128",
            "thumbnail": "",
            "created_time": 1466817822,
            "updated_time": 1466817829,
            "id": 107718128,
            "excerpt": "我早就说过了乌云就是一个钓鱼网站。",
            "content": "我早就说过了乌云就是一个钓鱼网站。",
            "is_copyable": true,
            "author": {
                "is_org": false,
                "avatar_url_template": "https://pic3.zhimg.com/e59aeb8898c50a830976297787cdce86_{size}.jpg",
                "gender": 1,
                "type": "people",
                "url": "https://www.zhihu.com/api/v4/people/dcddea61834f6b2dcb515f393fe29575",
                "url_token": "bhuztez",
                "user_type": "people",
                "headline": "正在找工作 ...",
                "badge": [],
                "is_advertiser": false,
                "name": "bhuztez",
                "avatar_url": "https://pic3.zhimg.com/e59aeb8898c50a830976297787cdce86_is.jpg",
                "id": "dcddea61834f6b2dcb515f393fe29575"
            },
            "extras": "",
            "question": {
                "title": "如何看待白帽子在乌云网提交世纪佳缘网漏洞后被抓？",
                "updated_time": 1466761071,
                "url": "https://www.zhihu.com/api/v4/questions/47775182",
                "type": "question",
                "created": 1466749853,
                "question_type": "normal",
                "id": 47775182
            }
        },
        {
            "type": "answer",
            "is_collapsed": false,
            "url": "https://www.zhihu.com/api/v4/answers/107554325",
            "thumbnail": "",
            "created_time": 1466736196,
            "updated_time": 1466736832,
            "id": 107554325,
            "excerpt": "前一篇刚刚黑了轮子哥，这一篇就开始吹嘘自己重新发明的轮子是多么高明。 Erlang/OTP自从2005年就已经有Dialyzer/Typer了。PySonar一个2009年才出来的玩具，有什么好吹的。Typer告诉你可能有A, B，实际运行过程中出现C，肯定是会出异常的。PySonar，告诉你可能出现A, B，实际运行过程中出现C，那也是很正常的。Typer能分析出pos_integer(), PySonar只能分析出int。Typer能充分利用多核，PySonar不过是一个单线程的玩具。HiPE会用…",
            "content": "前一篇刚刚黑了轮子哥，这一篇就开始吹嘘自己重新发明的轮子是多么高明。<br><br>Erlang/OTP自从2005年就已经有Dialyzer/Typer了。PySonar一个2009年才出来的玩具，有什么好吹的。Typer告诉你可能有A, B，实际运行过程中出现C，肯定是会出异常的。PySonar，告诉你可能出现A, B，实际运行过程中出现C，那也是很正常的。Typer能分析出pos_integer(), PySonar只能分析出int。Typer能充分利用多核，PySonar不过是一个单线程的玩具。HiPE会用类型推导得出的类型信息将Erlang编译成更高效的原生代码，(尽管这个功能我看大部分时候就是用来加速Dialyzer/Typer的)，PySonar的运行速度不提也罢。<br><br>我相信PySonar的思路是错的。像Python这种语言，像现在PySonar这样不以正确的结果为目标，搞不好把PyPy的JIT里收集的信息直接dump出来还容易一点。",
            "is_copyable": true,
            "author": {
                "is_org": false,
                "avatar_url_template": "https://pic3.zhimg.com/e59aeb8898c50a830976297787cdce86_{size}.jpg",
                "gender": 1,
                "type": "people",
                "url": "https://www.zhihu.com/api/v4/people/dcddea61834f6b2dcb515f393fe29575",
                "url_token": "bhuztez",
                "user_type": "people",
                "headline": "正在找工作 ...",
                "badge": [],
                "is_advertiser": false,
                "name": "bhuztez",
                "avatar_url": "https://pic3.zhimg.com/e59aeb8898c50a830976297787cdce86_is.jpg",
                "id": "dcddea61834f6b2dcb515f393fe29575"
            },
            "extras": "",
            "question": {
                "title": "如何评价王垠博文《PySonar的价值和意义》？",
                "updated_time": 1466731589,
                "url": "https://www.zhihu.com/api/v4/questions/47762484",
                "type": "question",
                "created": 1466731589,
                "question_type": "normal",
                "id": 47762484
            }
        },
        {
            "type": "answer",
            "is_collapsed": false,
            "url": "https://www.zhihu.com/api/v4/answers/107537289",
            "thumbnail": "",
            "created_time": 1466729762,
            "updated_time": 1466729819,
            "id": 107537289,
            "excerpt": "因为有一本书叫再见Matlab，曾老师教你用Mathematica做数值计算。",
            "content": "因为有一本书叫再见Matlab，曾老师教你用Mathematica做数值计算。",
            "is_copyable": true,
            "author": {
                "is_org": false,
                "avatar_url_template": "https://pic3.zhimg.com/e59aeb8898c50a830976297787cdce86_{size}.jpg",
                "gender": 1,
                "type": "people",
                "url": "https://www.zhihu.com/api/v4/people/dcddea61834f6b2dcb515f393fe29575",
                "url_token": "bhuztez",
                "user_type": "people",
                "headline": "正在找工作 ...",
                "badge": [],
                "is_advertiser": false,
                "name": "bhuztez",
                "avatar_url": "https://pic3.zhimg.com/e59aeb8898c50a830976297787cdce86_is.jpg",
                "id": "dcddea61834f6b2dcb515f393fe29575"
            },
            "extras": "",
            "question": {
                "title": "曾博为什么又叫曾老师？",
                "updated_time": 1484556826,
                "url": "https://www.zhihu.com/api/v4/questions/47749861",
                "type": "question",
                "created": 1466688407,
                "question_type": "normal",
                "id": 47749861
            }
        },
        {
            "type": "answer",
            "is_collapsed": false,
            "url": "https://www.zhihu.com/api/v4/answers/107128640",
            "thumbnail": "",
            "created_time": 1466511644,
            "updated_time": 1466673186,
            "id": 107128640,
            "excerpt": "这明明是勤奋好学的大哥向教授讲述自己的发现，结果被不要脸的教授强行收录到自己的书里。还要在报纸上借这位大哥的发现给自己的书打广告。这个论文写出来有没有杂志会收我不知道，但我知道arXiv上也是有这种类型的论文的。http://arxiv.org/abs/1305.1867 。就算不能发论文，哪怕只是发到OEIS上 Carmichael numbers ，还能让全世界人都看到。被这根本没人看的书收录，有啥意义？ 讲道理，对比双方的学习条件和取得的成就，这位大哥很好啊，…",
            "content": "这明明是勤奋好学的大哥向教授讲述自己的发现，结果被不要脸的教授强行收录到自己的书里。还要在报纸上借这位大哥的发现给自己的书打广告。这个论文写出来有没有杂志会收我不知道，但我知道arXiv上也是有这种类型的论文的。<a href=\"https://link.zhihu.com/?target=http%3A//arxiv.org/abs/1305.1867\" class=\" external\" target=\"_blank\" rel=\"nofollow noreferrer\"><span class=\"invisible\">http://</span><span class=\"visible\">arxiv.org/abs/1305.1867</span><span class=\"invisible\"></span><i class=\"icon-external\"></i></a> 。就算不能发论文，哪怕只是发到OEIS上 <a class=\" wrap external\" href=\"https://link.zhihu.com/?target=http%3A//oeis.org/wiki/Carmichael_numbers\" target=\"_blank\" rel=\"nofollow noreferrer\">Carmichael numbers<i class=\"icon-external\"></i></a>，还能让全世界人都看到。被这根本没人看的书收录，有啥意义？<br><br>讲道理，对比双方的学习条件和取得的成就，这位大哥很好啊，不过蔡教授恐怕连民科都算不上。蔡大教授的论文是什么水平？<a href=\"https://link.zhihu.com/?target=http%3A//arxiv.org/abs/1310.0898\" class=\" wrap external\" target=\"_blank\" rel=\"nofollow noreferrer\"> http://arxiv.org/abs/1310.0898<i class=\"icon-external\"></i></a> 用他自己的话说，论证的过程比较简短，那凭什么可以作为一篇严肃的学术论文发表？<br><br>看到这位大哥对数学这么有热情，有不少发现，蔡教授不给人指条路，怎么把一些比较好的成果公布出去，有哪些不足可以看什么书继续学习，反倒先惦记起自己的书。<br><br>明明是我先提问的。<a class=\"internal\" href=\"https://www.zhihu.com/question/47640416\">为啥三天两头能在报纸上看到浙大蔡天新教授的新闻还有他为什么是数学教授？ - 三本大学</a> 怎么都在这里回答<br><br>-----------------------------------<br><br>信不信由你。十多年前的事。像我读的那个垃圾高中，几乎不会有什么有头有脸的人会来讲座。突然有一天，说有个浙大数学教授愿意来讲座，据说还会写诗。大家都很期待。结果万万没想到，他就是报了一遍他周游列国的流水帐，主要内容就是重复很多遍，他到了哪里念了两句诗，又去下一个地方了。是唯一一次获得几百名师生一致差评的讲座。还有一个小插曲，似乎是为了显示他去的国家多，他在开始前还说答对他一个问题，他就送一个硬币，每个都是不同国家的。不知道为啥，他也没记谁答了他的问题，也许是因为他记忆力惊人吧。可是到最后，那些回答他无聊问题的同学啥也没拿到，全傻眼了，哈哈哈哈。",
            "is_copyable": true,
            "author": {
                "is_org": false,
                "avatar_url_template": "https://pic3.zhimg.com/e59aeb8898c50a830976297787cdce86_{size}.jpg",
                "gender": 1,
                "type": "people",
                "url": "https://www.zhihu.com/api/v4/people/dcddea61834f6b2dcb515f393fe29575",
                "url_token": "bhuztez",
                "user_type": "people",
                "headline": "正在找工作 ...",
                "badge": [],
                "is_advertiser": false,
                "name": "bhuztez",
                "avatar_url": "https://pic3.zhimg.com/e59aeb8898c50a830976297787cdce86_is.jpg",
                "id": "dcddea61834f6b2dcb515f393fe29575"
            },
            "extras": "",
            "question": {
                "title": "如何看待浙江大学数学教授邀请物流工人参加数学讨论？",
                "updated_time": 1466520355,
                "url": "https://www.zhihu.com/api/v4/questions/47648694",
                "type": "question",
                "created": 1466464266,
                "question_type": "normal",
                "id": 47648694
            }
        },
        {
            "type": "answer",
            "is_collapsed": false,
            "url": "https://www.zhihu.com/api/v4/answers/107090223",
            "thumbnail": "",
            "created_time": 1466496610,
            "updated_time": 1467899874,
            "id": 107090223,
            "excerpt": "俗话说 two turkeys do not make an eagle 。 Torch的C核心在很多评测中都表现出了更好的速度 瓶颈是memory bandwidth吧。用啥都不会多大区别的。 不考虑LUA以及C核心的先进性 Torch哪里先进了？Torch在模型里引入Explicit Parallelism就是错的。对于不同的CPU, GPU，最佳的分块都是不同的，你在模型里就指定了，后端可就只能干瞪眼了。Implicit Parrallelism才是最好的。 但现在已经是2016年了，框架不但有，而且还有很多，还有…",
            "content": "俗话说 two turkeys do not make an eagle 。<br><br><blockquote>Torch的C核心在很多评测中都表现出了更好的速度<br></blockquote><br>瓶颈是memory bandwidth吧。用啥都不会多大区别的。<br><br><blockquote>不考虑LUA以及C核心的先进性</blockquote><br>Torch哪里先进了？Torch在模型里引入Explicit Parallelism就是错的。对于不同的CPU, GPU，最佳的分块都是不同的，你在模型里就指定了，后端可就只能干瞪眼了。Implicit Parrallelism才是最好的。<br><br><blockquote>但现在已经是2016年了，框架不但有，而且还有很多，还有很好<br></blockquote><br>一个能用的都没有。谢谢。<br><br>你学C++有啥用啊。还不赶紧来学习一个<a href=\"https://zhuanlan.zhihu.com/p/21519402\" class=\"internal\"> 下一代深度学习框架技术内幕</a>",
            "is_copyable": true,
            "author": {
                "is_org": false,
                "avatar_url_template": "https://pic3.zhimg.com/e59aeb8898c50a830976297787cdce86_{size}.jpg",
                "gender": 1,
                "type": "people",
                "url": "https://www.zhihu.com/api/v4/people/dcddea61834f6b2dcb515f393fe29575",
                "url_token": "bhuztez",
                "user_type": "people",
                "headline": "正在找工作 ...",
                "badge": [],
                "is_advertiser": false,
                "name": "bhuztez",
                "avatar_url": "https://pic3.zhimg.com/e59aeb8898c50a830976297787cdce86_is.jpg",
                "id": "dcddea61834f6b2dcb515f393fe29575"
            },
            "extras": "",
            "question": {
                "title": "ConvNet实现之一caffe的作者们会向Torch学习其先进之处吗？",
                "updated_time": 1457586666,
                "url": "https://www.zhihu.com/api/v4/questions/41215244",
                "type": "question",
                "created": 1457586290,
                "question_type": "normal",
                "id": 41215244
            }
        },
        {
            "type": "answer",
            "is_collapsed": false,
            "url": "https://www.zhihu.com/api/v4/answers/106979862",
            "thumbnail": "",
            "created_time": 1466435732,
            "updated_time": 1466472075,
            "id": 106979862,
            "excerpt": "别的我不知道，我只知道千万不要像某脑残字体格式，偏移量的起始地址是从其所在位置开始算的。大致长这样 offset of x[0] x[1] x[2] \n 3 3 3 x[0] x[1] x[2]\n",
            "content": "别的我不知道，我只知道千万不要像某脑残字体格式，偏移量的起始地址是从其所在位置开始算的。大致长这样<br><br><div class=\"highlight\"><pre><code class=\"language-text\">offset of x[0]    x[1]    x[2]  \n            3       3       3     x[0]   x[1]   x[2]\n</code></pre></div>",
            "is_copyable": true,
            "author": {
                "is_org": false,
                "avatar_url_template": "https://pic3.zhimg.com/e59aeb8898c50a830976297787cdce86_{size}.jpg",
                "gender": 1,
                "type": "people",
                "url": "https://www.zhihu.com/api/v4/people/dcddea61834f6b2dcb515f393fe29575",
                "url_token": "bhuztez",
                "user_type": "people",
                "headline": "正在找工作 ...",
                "badge": [],
                "is_advertiser": false,
                "name": "bhuztez",
                "avatar_url": "https://pic3.zhimg.com/e59aeb8898c50a830976297787cdce86_is.jpg",
                "id": "dcddea61834f6b2dcb515f393fe29575"
            },
            "extras": "",
            "question": {
                "title": "设计应用的二进制存储格式有什么要点？",
                "updated_time": 1466369805,
                "url": "https://www.zhihu.com/api/v4/questions/47613023",
                "type": "question",
                "created": 1466361159,
                "question_type": "normal",
                "id": 47613023
            }
        },
        {
            "type": "answer",
            "is_collapsed": false,
            "url": "https://www.zhihu.com/api/v4/answers/106979078",
            "thumbnail": "",
            "created_time": 1466435471,
            "updated_time": 1466435508,
            "id": 106979078,
            "excerpt": "谁邀请我的。我早就说过了，无论是用编辑器还是IDE，都只能说明你用的语言太烂了，不能一行把程序写完。一行就能把程序写完，还要啥编辑器，IDE，还讲究什么软件工程。统统都不需要了。毕竟什么都不用才是最好的。口诀编程才是最酷的。",
            "content": "谁邀请我的。我早就说过了，无论是用编辑器还是IDE，都只能说明你用的语言太烂了，不能一行把程序写完。一行就能把程序写完，还要啥编辑器，IDE，还讲究什么软件工程。统统都不需要了。毕竟什么都不用才是最好的。口诀编程才是最酷的。",
            "is_copyable": true,
            "author": {
                "is_org": false,
                "avatar_url_template": "https://pic3.zhimg.com/e59aeb8898c50a830976297787cdce86_{size}.jpg",
                "gender": 1,
                "type": "people",
                "url": "https://www.zhihu.com/api/v4/people/dcddea61834f6b2dcb515f393fe29575",
                "url_token": "bhuztez",
                "user_type": "people",
                "headline": "正在找工作 ...",
                "badge": [],
                "is_advertiser": false,
                "name": "bhuztez",
                "avatar_url": "https://pic3.zhimg.com/e59aeb8898c50a830976297787cdce86_is.jpg",
                "id": "dcddea61834f6b2dcb515f393fe29575"
            },
            "extras": "",
            "question": {
                "title": "为什么很多人认为编辑器比 IDE 更酷？",
                "updated_time": 1466074721,
                "url": "https://www.zhihu.com/api/v4/questions/47502517",
                "type": "question",
                "created": 1466063241,
                "question_type": "normal",
                "id": 47502517
            }
        },
        {
            "type": "answer",
            "is_collapsed": false,
            "url": "https://www.zhihu.com/api/v4/answers/106954767",
            "thumbnail": "",
            "created_time": 1466425612,
            "updated_time": 1466428005,
            "id": 106954767,
            "excerpt": "座位当然不够啦。毕竟轮子哥一人能演十个角色，只要占五个座位。",
            "content": "座位当然不够啦。毕竟轮子哥一人能演十个角色，只要占五个座位。",
            "is_copyable": true,
            "author": {
                "is_org": false,
                "avatar_url_template": "https://pic3.zhimg.com/e59aeb8898c50a830976297787cdce86_{size}.jpg",
                "gender": 1,
                "type": "people",
                "url": "https://www.zhihu.com/api/v4/people/dcddea61834f6b2dcb515f393fe29575",
                "url_token": "bhuztez",
                "user_type": "people",
                "headline": "正在找工作 ...",
                "badge": [],
                "is_advertiser": false,
                "name": "bhuztez",
                "avatar_url": "https://pic3.zhimg.com/e59aeb8898c50a830976297787cdce86_is.jpg",
                "id": "dcddea61834f6b2dcb515f393fe29575"
            },
            "extras": "",
            "question": {
                "title": "vczh（轮子哥）为什么没参加2016年6月20日播出的有关程序员那期的《职人介绍所》？",
                "updated_time": 1480301461,
                "url": "https://www.zhihu.com/api/v4/questions/47614543",
                "type": "question",
                "created": 1466380965,
                "question_type": "normal",
                "id": 47614543
            }
        },
        {
            "type": "answer",
            "is_collapsed": false,
            "url": "https://www.zhihu.com/api/v4/answers/106845022",
            "thumbnail": "",
            "created_time": 1466386411,
            "updated_time": 1466386411,
            "id": 106845022,
            "excerpt": "https://twitter.com/FioraAeterna/status/675066780205891584 ",
            "content": "<a href=\"https://link.zhihu.com/?target=https%3A//twitter.com/FioraAeterna/status/675066780205891584\" class=\" external\" target=\"_blank\" rel=\"nofollow noreferrer\"><span class=\"invisible\">https://</span><span class=\"visible\">twitter.com/FioraAetern</span><span class=\"invisible\">a/status/675066780205891584</span><span class=\"ellipsis\"></span><i class=\"icon-external\"></i></a><br><noscript><img data-rawheight=\"352\" data-rawwidth=\"602\" src=\"https://pic2.zhimg.com/80198847b2df7cbe1e0bf8e4145247a9_b.png\" class=\"origin_image zh-lightbox-thumb\" width=\"602\" data-original=\"https://pic2.zhimg.com/80198847b2df7cbe1e0bf8e4145247a9_r.png\"></noscript><img data-rawheight=\"352\" data-rawwidth=\"602\" src=\"//zhstatic.zhihu.com/assets/zhihu/ztext/whitedot.jpg\" class=\"origin_image zh-lightbox-thumb lazy\" width=\"602\" data-original=\"https://pic2.zhimg.com/80198847b2df7cbe1e0bf8e4145247a9_r.png\" data-actualsrc=\"https://pic2.zhimg.com/80198847b2df7cbe1e0bf8e4145247a9_b.png\">",
            "is_copyable": true,
            "author": {
                "is_org": false,
                "avatar_url_template": "https://pic3.zhimg.com/e59aeb8898c50a830976297787cdce86_{size}.jpg",
                "gender": 1,
                "type": "people",
                "url": "https://www.zhihu.com/api/v4/people/dcddea61834f6b2dcb515f393fe29575",
                "url_token": "bhuztez",
                "user_type": "people",
                "headline": "正在找工作 ...",
                "badge": [],
                "is_advertiser": false,
                "name": "bhuztez",
                "avatar_url": "https://pic3.zhimg.com/e59aeb8898c50a830976297787cdce86_is.jpg",
                "id": "dcddea61834f6b2dcb515f393fe29575"
            },
            "extras": "",
            "question": {
                "title": "谈谈你对\"GPU/CPU集群下做到Data/Model Parallelism的区别\"的理解？",
                "updated_time": 1436276573,
                "url": "https://www.zhihu.com/api/v4/questions/31999064",
                "type": "question",
                "created": 1436276573,
                "question_type": "normal",
                "id": 31999064
            }
        },
        {
            "type": "answer",
            "is_collapsed": false,
            "url": "https://www.zhihu.com/api/v4/answers/106744205",
            "thumbnail": "",
            "created_time": 1466324180,
            "updated_time": 1466324879,
            "id": 106744205,
            "excerpt": "曾老师你怎么可以因为自己比轮子哥多一点微小的分辨能力而沾沾自喜呢。你这样做和轮子哥又有啥区别呢。 他在我小学的时候就给我搞了一大堆奥赛的书。我那个时候也看下去了，因为除了看电视以外实在没别的事情干了。当时的电脑还是富二代才买得起，网络还是一秒几个K的，没有任何娱乐活动。 奥赛的书还挺好看。想当年小学的时候每次发烧了，躺在床上，我爸就给我念，然后我给答案。久而久之我的自学能力得到了迅猛的提高，总是超…",
            "content": "曾老师你怎么可以因为自己比轮子哥多一点微小的分辨能力而沾沾自喜呢。你这样做和轮子哥又有啥区别呢。<br><br><blockquote>他在我小学的时候就给我搞了一大堆奥赛的书。我那个时候也看下去了，因为除了看电视以外实在没别的事情干了。当时的电脑还是富二代才买得起，网络还是一秒几个K的，没有任何娱乐活动。<br><br>奥赛的书还挺好看。想当年小学的时候每次发烧了，躺在床上，我爸就给我念，然后我给答案。久而久之我的自学能力得到了迅猛的提高，总是超前若干年完成数学的学习任务。<br><br><a class=\"internal\" href=\"https://www.zhihu.com/question/37474573/answer/79963260\">成年以后，父亲充当了你生命中什么样的角色？ - vczh 的回答</a></blockquote><br>轮子哥没有分辨能力，明明被鱼目混珠的垃圾奥数书坑了，还觉得自己很牛逼。<br><br><blockquote><p>这是个图论问题，无脑解决的话，可以创造若干个节点，每个节点是每一种水的分布的可能，譬如说0,0,10啊，3,4,3啊，要点就是都是整数，而且加起来是10，并且每个桶不能装超过自己容量的水。后面就简单了，两层遍历所有节点，只要一个节点能通过一次操作到达另一个节点，就连一条线，譬如说0,0,10-&gt;0,7,3，整个图就这么做出来了。然后起点0,0,10和终点0,5,5你都是知道的，直接上Dijkstra最短路径算法。</p><br><p>现在的人还是太没有想象力了，为什么一定要new出一个图才能做Dijkstra呢，太烂了。</p><br><a class=\"internal\" href=\"https://www.zhihu.com/question/28830426/answer/42239987\">10L 瓶装水通过一个7L 瓶和3L 瓶平分成两瓶5L 水，有什么数学方法计算此类问题？ - vczh 的回答</a></blockquote><br>小学奥数经典例题water jug非常简单，正经的奥数书里都会讲这个题的。你看轮子哥连这种问题还要暴力搜索，竟然还好意思说自己看过小学奥数书。",
            "is_copyable": true,
            "author": {
                "is_org": false,
                "avatar_url_template": "https://pic3.zhimg.com/e59aeb8898c50a830976297787cdce86_{size}.jpg",
                "gender": 1,
                "type": "people",
                "url": "https://www.zhihu.com/api/v4/people/dcddea61834f6b2dcb515f393fe29575",
                "url_token": "bhuztez",
                "user_type": "people",
                "headline": "正在找工作 ...",
                "badge": [],
                "is_advertiser": false,
                "name": "bhuztez",
                "avatar_url": "https://pic3.zhimg.com/e59aeb8898c50a830976297787cdce86_is.jpg",
                "id": "dcddea61834f6b2dcb515f393fe29575"
            },
            "extras": "",
            "question": {
                "title": "微软这么受人尊敬是不是因为他给了很多差生以希望？",
                "updated_time": 1466318908,
                "url": "https://www.zhihu.com/api/v4/questions/47594085",
                "type": "question",
                "created": 1466318908,
                "question_type": "normal",
                "id": 47594085
            }
        },
        {
            "type": "answer",
            "is_collapsed": false,
            "url": "https://www.zhihu.com/api/v4/answers/106632200",
            "thumbnail": "",
            "created_time": 1466254514,
            "updated_time": 1466258176,
            "id": 106632200,
            "excerpt": "这个主要是因为numpy没有引入从tensor那里借鉴来的统一的rank记号。numpy算好了，一堆近几年才出现的深度学习框架，有的数据结构命名成tensor的，有名字里带tensor的，没一个有这种记号的。 比如J语言 (+/ .*) 在这里相当于 np.dot 。 A =: 2 2 $ 1 2 3 4\n B =: 2 2 $ 5 6 7 8\n A\n1 2\n3 4\n B\n5 6\n7 8\n A ((+/ .*)\"1 1)\"1 2 B\n17 23\n39 53\n 也可以展开写成 (+/\"1) A (*\"1 1)\"1 2 B\n17 23\n39 53\n 第二种写法在J语言里的问题是会产…",
            "content": "这个主要是因为numpy没有引入从tensor那里借鉴来的统一的rank记号。numpy算好了，一堆近几年才出现的深度学习框架，有的数据结构命名成tensor的，有名字里带tensor的，没一个有这种记号的。<br><br>比如J语言 (+/ .*) 在这里相当于 np.dot 。<br><br><div class=\"highlight\"><pre><code class=\"language-text\">   A =: 2 2 $ 1 2 3 4\n   B =: 2 2 $ 5 6 7 8\n   A\n1 2\n3 4\n   B\n5 6\n7 8\n   A ((+/ .*)\"1 1)\"1 2 B\n17 23\n39 53\n</code></pre></div><br>也可以展开写成<br><br><div class=\"highlight\"><pre><code class=\"language-text\">   (+/\"1) A (*\"1 1)\"1 2 B\n17 23\n39 53\n</code></pre></div><br>第二种写法在J语言里的问题是会产生一个很大的中间数组 ???<br><br>我弄的那个深度学习框架，因为是编译执行的，中间这个数组就自动被编译掉了，只(需要)支持第二种写法。(因为什么都不支持才是最好的，所以也不支持运算符优先级，所有括号都不得省略。另外reduce更加高级一点，可以reduce多维的，所以需要写1) <br><br><div class=\"highlight\"><pre><code class=\"language-text\">(((reduce 1 +)\"1) (A ((*\"1 1)\"1 2) B))\n</code></pre></div><br>现在正在裁减自动求导那部分功能，毕竟是要写个教程，搞太复杂不好。",
            "is_copyable": true,
            "author": {
                "is_org": false,
                "avatar_url_template": "https://pic3.zhimg.com/e59aeb8898c50a830976297787cdce86_{size}.jpg",
                "gender": 1,
                "type": "people",
                "url": "https://www.zhihu.com/api/v4/people/dcddea61834f6b2dcb515f393fe29575",
                "url_token": "bhuztez",
                "user_type": "people",
                "headline": "正在找工作 ...",
                "badge": [],
                "is_advertiser": false,
                "name": "bhuztez",
                "avatar_url": "https://pic3.zhimg.com/e59aeb8898c50a830976297787cdce86_is.jpg",
                "id": "dcddea61834f6b2dcb515f393fe29575"
            },
            "extras": "",
            "question": {
                "title": "numpy中是否有什么办法扩展dot函数？",
                "updated_time": 1466393407,
                "url": "https://www.zhihu.com/api/v4/questions/46616756",
                "type": "question",
                "created": 1463896818,
                "question_type": "normal",
                "id": 46616756
            }
        },
        {
            "type": "answer",
            "is_collapsed": false,
            "url": "https://www.zhihu.com/api/v4/answers/105733723",
            "thumbnail": "",
            "created_time": 1465794613,
            "updated_time": 1465804725,
            "id": 105733723,
            "excerpt": "你应该问为什么要变，而不是为什么不变。用的好好的为啥要变？",
            "content": "你应该问为什么要变，而不是为什么不变。用的好好的为啥要变？",
            "is_copyable": true,
            "author": {
                "is_org": false,
                "avatar_url_template": "https://pic3.zhimg.com/e59aeb8898c50a830976297787cdce86_{size}.jpg",
                "gender": 1,
                "type": "people",
                "url": "https://www.zhihu.com/api/v4/people/dcddea61834f6b2dcb515f393fe29575",
                "url_token": "bhuztez",
                "user_type": "people",
                "headline": "正在找工作 ...",
                "badge": [],
                "is_advertiser": false,
                "name": "bhuztez",
                "avatar_url": "https://pic3.zhimg.com/e59aeb8898c50a830976297787cdce86_is.jpg",
                "id": "dcddea61834f6b2dcb515f393fe29575"
            },
            "extras": "",
            "question": {
                "title": "为什么感觉一种语言如果在语序进化的过程中，那么否定句，特殊疑问句等会比陈述句倾向于保留旧的语序?",
                "updated_time": 1465796053,
                "url": "https://www.zhihu.com/api/v4/questions/47388960",
                "type": "question",
                "created": 1465794092,
                "question_type": "normal",
                "id": 47388960
            }
        },
        {
            "type": "answer",
            "is_collapsed": false,
            "url": "https://www.zhihu.com/api/v4/answers/105596839",
            "thumbnail": "",
            "created_time": 1465722701,
            "updated_time": 1465722701,
            "id": 105596839,
            "excerpt": "看来他也知道了为什么21天能学通Erlang",
            "content": "看来他也知道了为什么21天能学通Erlang",
            "is_copyable": true,
            "author": {
                "is_org": false,
                "avatar_url_template": "https://pic3.zhimg.com/e59aeb8898c50a830976297787cdce86_{size}.jpg",
                "gender": 1,
                "type": "people",
                "url": "https://www.zhihu.com/api/v4/people/dcddea61834f6b2dcb515f393fe29575",
                "url_token": "bhuztez",
                "user_type": "people",
                "headline": "正在找工作 ...",
                "badge": [],
                "is_advertiser": false,
                "name": "bhuztez",
                "avatar_url": "https://pic3.zhimg.com/e59aeb8898c50a830976297787cdce86_is.jpg",
                "id": "dcddea61834f6b2dcb515f393fe29575"
            },
            "extras": "",
            "question": {
                "title": "如何看待“一年可以成长为全栈工程师”观点？",
                "updated_time": 1466384817,
                "url": "https://www.zhihu.com/api/v4/questions/47359997",
                "type": "question",
                "created": 1465719840,
                "question_type": "normal",
                "id": 47359997
            }
        },
        {
            "type": "answer",
            "is_collapsed": false,
            "url": "https://www.zhihu.com/api/v4/answers/105586677",
            "thumbnail": "",
            "created_time": 1465719420,
            "updated_time": 1465721198,
            "id": 105586677,
            "excerpt": "反对轮子哥误导人的说法。 GPL系列协议在我国是不受法律承认的这个说法是错的。 参考，当然第一个链接是标题党 中国法院为什么保护违反GPL软件协议的行为？ “开源”相关知识产权问题探讨 这起案件没找到原始判决书，但性质上应该是和下面这起案件类似的。 恒生电子股份有限公司、杭州恒生网络技术服务有限公司与王云敏、孙志彦等侵犯商业秘密纠纷一审民事判决书 按GPL的说法，假设A开发了以GPL协议发布的X软件，B的Y软件中用到…",
            "content": "反对轮子哥误导人的说法。<br><br>GPL系列协议在我国是不受法律承认的这个说法是错的。<br><br>参考，当然第一个链接是标题党<br><br><a href=\"https://link.zhihu.com/?target=http%3A//www.legalservice.cn/%25E4%25B8%25AD%25E5%259B%25BD%25E6%25B3%2595%25E9%2599%25A2%25E4%25B8%25BA%25E4%25BB%2580%25E4%25B9%2588%25E4%25BF%259D%25E6%258A%25A4%25E8%25BF%259D%25E5%258F%258Dgpl%25E8%25BD%25AF%25E4%25BB%25B6%25E5%258D%258F%25E8%25AE%25AE%25E7%259A%2584%25E8%25A1%258C%25E4%25B8%25BA%25EF%25BC%259F/\" class=\" wrap external\" target=\"_blank\" rel=\"nofollow noreferrer\">中国法院为什么保护违反GPL软件协议的行为？<i class=\"icon-external\"></i></a><br><a class=\" wrap external\" href=\"https://link.zhihu.com/?target=http%3A//www.pkulaw.cn/fulltext_form.aspx%3FGid%3D1778399205%26Db%3Dlawfirmarticles\" target=\"_blank\" rel=\"nofollow noreferrer\">“开源”相关知识产权问题探讨<i class=\"icon-external\"></i></a><br><br>这起案件没找到原始判决书，但性质上应该是和下面这起案件类似的。<br><br><a class=\" wrap external\" href=\"https://link.zhihu.com/?target=http%3A//wenshu.court.gov.cn/content/content%3FDocID%3D4212d748-f3a5-45be-8d9a-06dcb67f719e%26KeyWord%3D%25E5%25BC%2580%25E6%25BA%2590%257C%25E8%25BD%25AF%25E4%25BB%25B6\" target=\"_blank\" rel=\"nofollow noreferrer\">恒生电子股份有限公司、杭州恒生网络技术服务有限公司与王云敏、孙志彦等侵犯商业秘密纠纷一审民事判决书<i class=\"icon-external\"></i></a><br><br>按GPL的说法，假设A开发了以GPL协议发布的X软件，B的Y软件中用到了X，且B向C交付了Y软件。假如上面两个链接中提供的信息是无误的，我们可以肯定A和C是同一个人时，要求B遵守GPL这是能得到法院支持的。<br><br>问题出在案件中并不存在C。而是D作为B的员工，离开B时擅自拷贝了一份Y，这不构成B向D分发。所以，法院并没有就A和C不是同一个人时，B不向C公开Y的源代码是否合法作出裁决。法院只是简单说了在不违反现行中国法律的前提下，GPL是有效的。<br><br>直播姬这个情况是分发已经成立，所以某bilibili的竞争对手下载了直播姬，赶紧去告一告bilibili就能见分晓了<br><br>----------------------<br><br>另外，假设GPL是有效的，那么bilibili需要提供的是和发布的二进制程序严格对应的源代码，提供修改过的源代码是不符合GPL要求的。",
            "is_copyable": true,
            "author": {
                "is_org": false,
                "avatar_url_template": "https://pic3.zhimg.com/e59aeb8898c50a830976297787cdce86_{size}.jpg",
                "gender": 1,
                "type": "people",
                "url": "https://www.zhihu.com/api/v4/people/dcddea61834f6b2dcb515f393fe29575",
                "url_token": "bhuztez",
                "user_type": "people",
                "headline": "正在找工作 ...",
                "badge": [],
                "is_advertiser": false,
                "name": "bhuztez",
                "avatar_url": "https://pic3.zhimg.com/e59aeb8898c50a830976297787cdce86_is.jpg",
                "id": "dcddea61834f6b2dcb515f393fe29575"
            },
            "extras": "",
            "question": {
                "title": "如何看待bilibili直播姬疑似盗用obs代码？",
                "updated_time": 1465727362,
                "url": "https://www.zhihu.com/api/v4/questions/47335914",
                "type": "question",
                "created": 1465655772,
                "question_type": "normal",
                "id": 47335914
            }
        }
    ]
}